pyportainer/__init__.py
pyportainer/exceptions.py
pyportainer/py.typed
pyportainer/pyportainer.py
pyportainer/models/__init__.py
pyportainer/models/docker.py
pyportainer/models/docker_inspect.py
pyportainer/models/portainer.py
pyportainer-1.0.19.dist-info/METADATA
pyportainer-1.0.19.dist-info/WHEEL
pyportainer-1.0.19.dist-info/licenses/LICENSE
pyportainer-1.0.19.dist-info/RECORD
